braindecode/__init__.py
braindecode/classifier.py
braindecode/eegneuralnet.py
braindecode/regressor.py
braindecode/util.py
braindecode/version.py
braindecode/augmentation/__init__.py
braindecode/augmentation/base.py
braindecode/augmentation/functional.py
braindecode/augmentation/transforms.py
braindecode/datasets/__init__.py
braindecode/datasets/base.py
braindecode/datasets/bbci.py
braindecode/datasets/bcicomp.py
braindecode/datasets/bids.py
braindecode/datasets/mne.py
braindecode/datasets/moabb.py
braindecode/datasets/nmt.py
braindecode/datasets/sleep_physio_challe_18.py
braindecode/datasets/sleep_physionet.py
braindecode/datasets/tuh.py
braindecode/datasets/xy.py
braindecode/datautil/__init__.py
braindecode/datautil/serialization.py
braindecode/datautil/util.py
braindecode/functional/__init__.py
braindecode/functional/functions.py
braindecode/functional/initialization.py
braindecode/models/__init__.py
braindecode/models/atcnet.py
braindecode/models/attentionbasenet.py
braindecode/models/base.py
braindecode/models/biot.py
braindecode/models/contrawr.py
braindecode/models/ctnet.py
braindecode/models/deep4.py
braindecode/models/deepsleepnet.py
braindecode/models/eegconformer.py
braindecode/models/eeginception_erp.py
braindecode/models/eeginception_mi.py
braindecode/models/eegitnet.py
braindecode/models/eegminer.py
braindecode/models/eegnet.py
braindecode/models/eegnex.py
braindecode/models/eegresnet.py
braindecode/models/eegsimpleconv.py
braindecode/models/eegtcnet.py
braindecode/models/fbcnet.py
braindecode/models/fblightconvnet.py
braindecode/models/fbmsnet.py
braindecode/models/hybrid.py
braindecode/models/ifnet.py
braindecode/models/labram.py
braindecode/models/msvtnet.py
braindecode/models/sccnet.py
braindecode/models/shallow_fbcsp.py
braindecode/models/signal_jepa.py
braindecode/models/sinc_shallow.py
braindecode/models/sleep_stager_blanco_2020.py
braindecode/models/sleep_stager_chambon_2018.py
braindecode/models/sleep_stager_eldele_2021.py
braindecode-1.1.0.dist-info/licenses/LICENSE.txt
braindecode-1.1.0.dist-info/licenses/NOTICE.txt
braindecode-1.1.0.dist-info/METADATA
braindecode-1.1.0.dist-info/WHEEL
braindecode-1.1.0.dist-info/top_level.txt
braindecode-1.1.0.dist-info/RECORD
