Metadata-Version: 2.4
Name: braindecode
Version: 1.1.0
Summary: Deep learning software to decode EEG, ECG or MEG signals
Author-email: Robin Tibor Schirrmeister <robintibor@gmail.com>
Maintainer-email: Alexandre Gramfort <agramfort@meta.com>, Bruno Aristimunha Pinto <b.aristimunha@gmail.com>, Robin Tibor Schirrmeister <robintibor@gmail.com>
License: BSD-3-Clause
Project-URL: homepage, https://braindecode.org
Project-URL: repository, https://github.com/braindecode/braindecode
Project-URL: documentation, https://braindecode.org/stable/index.html
Keywords: python,deep-learning,neuroscience,pytorch,meg,eeg,neuroimaging,electroencephalography,magnetoencephalography,electrocorticography,ecog,electroencephalogram
Classifier: Development Status :: 3 - Alpha
Classifier: Intended Audience :: Developers
Classifier: Intended Audience :: Science/Research
Classifier: Topic :: Software Development :: Build Tools
Classifier: Topic :: Scientific/Engineering :: Artificial Intelligence
Classifier: License :: OSI Approved :: BSD License
Classifier: Programming Language :: Python :: 3.10
Classifier: Programming Language :: Python :: 3.11
Classifier: Programming Language :: Python :: 3.12
Requires-Python: >3.9
License-File: LICENSE.txt
License-File: NOTICE.txt
Requires-Dist: mne>=1.10.0
Requires-Dist: mne_bids>=0.16
Requires-Dist: numpy
Requires-Dist: pandas
Requires-Dist: scipy
Requires-Dist: matplotlib
Requires-Dist: h5py
Requires-Dist: skorch~=0.14.0
Requires-Dist: torch~=2.0
Requires-Dist: torchaudio~=2.0
Requires-Dist: einops
Requires-Dist: joblib
Requires-Dist: torchinfo~=1.8
Requires-Dist: wfdb
Requires-Dist: h5py
Requires-Dist: linear_attention_transformer
Requires-Dist: docstring_inheritance
Provides-Extra: moabb
Requires-Dist: moabb>=1.2.0; extra == "moabb"
Provides-Extra: tests
Requires-Dist: pytest; extra == "tests"
Requires-Dist: pytest-cov; extra == "tests"
Requires-Dist: codecov; extra == "tests"
Requires-Dist: pytest_cases; extra == "tests"
Requires-Dist: mypy; extra == "tests"
Provides-Extra: docs
Requires-Dist: sphinx_gallery; extra == "docs"
Requires-Dist: sphinx_rtd_theme; extra == "docs"
Requires-Dist: pydata_sphinx_theme; extra == "docs"
Requires-Dist: numpydoc; extra == "docs"
Requires-Dist: memory_profiler; extra == "docs"
Requires-Dist: pillow; extra == "docs"
Requires-Dist: ipython; extra == "docs"
Requires-Dist: sphinx_design; extra == "docs"
Requires-Dist: lightning; extra == "docs"
Requires-Dist: seaborn; extra == "docs"
Requires-Dist: pre-commit; extra == "docs"
Requires-Dist: openneuro-py; extra == "docs"
Dynamic: license-file
